{
  "actualizado": "2026-04-10T13:11:21.276699",
  "partidos": [
    {
      "id": 101,
      "fecha": 14,
      "dia": "Sáb 11/04",
      "fechaISO": "2026-04-11",
      "esHoy": false,
      "liga": "primera",
      "ligaNombre": "Liga Profesional",
      "local": {
        "nombre": "Riestra",
        "goles": null
      },
      "visitante": {
        "nombre": "Instituto",
        "goles": null
      },
      "hora": "10:00",
      "minuto": null,
      "estado": "programado"
    },
    {
      "id": 102,
      "fecha": 14,
      "dia": "Sáb 11/04",
      "fechaISO": "2026-04-11",
      "esHoy": false,
      "liga": "primera",
      "ligaNombre": "Liga Profesional",
      "local": {
        "nombre": "Ind. Rivadavia",
        "goles": null
      },
      "visitante": {
        "nombre": "Argentinos Juniors",
        "goles": null
      },
      "hora": "10:30",
      "minuto": null,
      "estado": "programado"
    },
    {
      "id": 103,
      "fecha": 14,
      "dia": "Sáb 11/04",
      "fechaISO": "2026-04-11",
      "esHoy": false,
      "liga": "primera",
      "ligaNombre": "Liga Profesional",
      "local": {
        "nombre": "Estudiantes",
        "goles": null
      },
      "visitante": {
        "nombre": "Union Santa Fe",
        "goles": null
      },
      "hora": "12:15",
      "minuto": null,
      "estado": "programado"
    },
    {
      "id": 104,
      "fecha": 14,
      "dia": "Sáb 11/04",
      "fechaISO": "2026-04-11",
      "esHoy": false,
      "liga": "primera",
      "ligaNombre": "Liga Profesional",
      "local": {
        "nombre": "Boca Juniors",
        "goles": null
      },
      "visitante": {
        "nombre": "Independiente",
        "goles": null
      },
      "hora": "14:30",
      "minuto": null,
      "estado": "programado"
    },
    {
      "id": 105,
      "fecha": 14,
      "dia": "Sáb 11/04",
      "fechaISO": "2026-04-11",
      "esHoy": false,
      "liga": "primera",
      "ligaNombre": "Liga Profesional",
      "local": {
        "nombre": "Estudiantes RC",
        "goles": null
      },
      "visitante": {
        "nombre": "Barracas Central",
        "goles": null
      },
      "hora": "16:45",
      "minuto": null,
      "estado": "programado"
    },
    {
      "id": 106,
      "fecha": 14,
      "dia": "Dom 12/04",
      "fechaISO": "2026-04-12",
      "esHoy": false,
      "liga": "primera",
      "ligaNombre": "Liga Profesional",
      "local": {
        "nombre": "Newells",
        "goles": null
      },
      "visitante": {
        "nombre": "San Lorenzo",
        "goles": null
      },
      "hora": "10:00",
      "minuto": null,
      "estado": "programado"
    },
    {
      "id": 107,
      "fecha": 14,
      "dia": "Dom 12/04",
      "fechaISO": "2026-04-12",
      "esHoy": false,
      "liga": "primera",
      "ligaNombre": "Liga Profesional",
      "local": {
        "nombre": "Platense",
        "goles": null
      },
      "visitante": {
        "nombre": "Gimnasia Mendoza",
        "goles": null
      },
      "hora": "10:00",
      "minuto": null,
      "estado": "programado"
    },
    {
      "id": 108,
      "fecha": 14,
      "dia": "Dom 12/04",
      "fechaISO": "2026-04-12",
      "esHoy": false,
      "liga": "primera",
      "ligaNombre": "Liga Profesional",
      "local": {
        "nombre": "Huracan",
        "goles": null
      },
      "visitante": {
        "nombre": "Rosario Central",
        "goles": null
      },
      "hora": "12:30",
      "minuto": null,
      "estado": "programado"
    },
    {
      "id": 109,
      "fecha": 14,
      "dia": "Dom 12/04",
      "fechaISO": "2026-04-12",
      "esHoy": false,
      "liga": "primera",
      "ligaNombre": "Liga Profesional",
      "local": {
        "nombre": "Atletico Tucuman",
        "goles": null
      },
      "visitante": {
        "nombre": "Tigre",
        "goles": null
      },
      "hora": "12:30",
      "minuto": null,
      "estado": "programado"
    },
    {
      "id": 110,
      "fecha": 14,
      "dia": "Dom 12/04",
      "fechaISO": "2026-04-12",
      "esHoy": false,
      "liga": "primera",
      "ligaNombre": "Liga Profesional",
      "local": {
        "nombre": "Racing Club",
        "goles": null
      },
      "visitante": {
        "nombre": "River Plate",
        "goles": null
      },
      "hora": "15:00",
      "minuto": null,
      "estado": "programado"
    },
    {
      "id": 111,
      "fecha": 14,
      "dia": "Lun 13/04",
      "fechaISO": "2026-04-13",
      "esHoy": false,
      "liga": "primera",
      "ligaNombre": "Liga Profesional",
      "local": {
        "nombre": "Defensa y Justicia",
        "goles": null
      },
      "visitante": {
        "nombre": "Talleres",
        "goles": null
      },
      "hora": "11:30",
      "minuto": null,
      "estado": "programado"
    },
    {
      "id": 112,
      "fecha": 14,
      "dia": "Lun 13/04",
      "fechaISO": "2026-04-13",
      "esHoy": false,
      "liga": "primera",
      "ligaNombre": "Liga Profesional",
      "local": {
        "nombre": "Sarmiento",
        "goles": null
      },
      "visitante": {
        "nombre": "Gimnasia LP",
        "goles": null
      },
      "hora": "11:30",
      "minuto": null,
      "estado": "programado"
    },
    {
      "id": 113,
      "fecha": 14,
      "dia": "Lun 13/04",
      "fechaISO": "2026-04-13",
      "esHoy": false,
      "liga": "primera",
      "ligaNombre": "Liga Profesional",
      "local": {
        "nombre": "Lanus",
        "goles": null
      },
      "visitante": {
        "nombre": "Banfield",
        "goles": null
      },
      "hora": "14:00",
      "minuto": null,
      "estado": "programado"
    },
    {
      "id": 114,
      "fecha": 14,
      "dia": "Lun 13/04",
      "fechaISO": "2026-04-13",
      "esHoy": false,
      "liga": "primera",
      "ligaNombre": "Liga Profesional",
      "local": {
        "nombre": "Velez Sarsfield",
        "goles": null
      },
      "visitante": {
        "nombre": "Central Cordoba",
        "goles": null
      },
      "hora": "16:30",
      "minuto": null,
      "estado": "programado"
    },
    {
      "id": 115,
      "fecha": 9,
      "dia": "Sáb 11/04",
      "fechaISO": "2026-04-11",
      "esHoy": false,
      "liga": "nacional",
      "ligaNombre": "Primera Nacional",
      "local": {
        "nombre": "San Miguel",
        "goles": null
      },
      "visitante": {
        "nombre": "Morón",
        "goles": null
      },
      "hora": "10:30",
      "minuto": null,
      "estado": "programado"
    },
    {
      "id": 116,
      "fecha": 9,
      "dia": "Sáb 11/04",
      "fechaISO": "2026-04-11",
      "esHoy": false,
      "liga": "nacional",
      "ligaNombre": "Primera Nacional",
      "local": {
        "nombre": "San Telmo",
        "goles": null
      },
      "visitante": {
        "nombre": "Godoy Cruz",
        "goles": null
      },
      "hora": "10:30",
      "minuto": null,
      "estado": "programado"
    },
    {
      "id": 117,
      "fecha": 9,
      "dia": "Sáb 11/04",
      "fechaISO": "2026-04-11",
      "esHoy": false,
      "liga": "nacional",
      "ligaNombre": "Primera Nacional",
      "local": {
        "nombre": "Almagro",
        "goles": null
      },
      "visitante": {
        "nombre": "Patronato",
        "goles": null
      },
      "hora": "10:30",
      "minuto": null,
      "estado": "programado"
    },
    {
      "id": 118,
      "fecha": 9,
      "dia": "Sáb 11/04",
      "fechaISO": "2026-04-11",
      "esHoy": false,
      "liga": "nacional",
      "ligaNombre": "Primera Nacional",
      "local": {
        "nombre": "Colón",
        "goles": null
      },
      "visitante": {
        "nombre": "Racing (Cba)",
        "goles": null
      },
      "hora": "14:00",
      "minuto": null,
      "estado": "programado"
    },
    {
      "id": 119,
      "fecha": 9,
      "dia": "Dom 12/04",
      "fechaISO": "2026-04-12",
      "esHoy": false,
      "liga": "nacional",
      "ligaNombre": "Primera Nacional",
      "local": {
        "nombre": "Acassuso",
        "goles": null
      },
      "visitante": {
        "nombre": "Los Andes",
        "goles": null
      },
      "hora": "10:00",
      "minuto": null,
      "estado": "programado"
    },
    {
      "id": 120,
      "fecha": 9,
      "dia": "Dom 12/04",
      "fechaISO": "2026-04-12",
      "esHoy": false,
      "liga": "nacional",
      "ligaNombre": "Primera Nacional",
      "local": {
        "nombre": "Ferro",
        "goles": null
      },
      "visitante": {
        "nombre": "Estudiantes",
        "goles": null
      },
      "hora": "10:00",
      "minuto": null,
      "estado": "programado"
    },
    {
      "id": 121,
      "fecha": 9,
      "dia": "Dom 12/04",
      "fechaISO": "2026-04-12",
      "esHoy": false,
      "liga": "nacional",
      "ligaNombre": "Primera Nacional",
      "local": {
        "nombre": "Defensores",
        "goles": null
      },
      "visitante": {
        "nombre": "Bolivar",
        "goles": null
      },
      "hora": "10:00",
      "minuto": null,
      "estado": "programado"
    },
    {
      "id": 122,
      "fecha": 9,
      "dia": "Dom 12/04",
      "fechaISO": "2026-04-12",
      "esHoy": false,
      "liga": "nacional",
      "ligaNombre": "Primera Nacional",
      "local": {
        "nombre": "Chacarita",
        "goles": null
      },
      "visitante": {
        "nombre": "Gimnasia y Tiro",
        "goles": null
      },
      "hora": "10:00",
      "minuto": null,
      "estado": "programado"
    },
    {
      "id": 123,
      "fecha": 9,
      "dia": "Dom 12/04",
      "fechaISO": "2026-04-12",
      "esHoy": false,
      "liga": "nacional",
      "ligaNombre": "Primera Nacional",
      "local": {
        "nombre": "Temperley",
        "goles": null
      },
      "visitante": {
        "nombre": "Quilmes",
        "goles": null
      },
      "hora": "10:00",
      "minuto": null,
      "estado": "programado"
    },
    {
      "id": 124,
      "fecha": 9,
      "dia": "Dom 12/04",
      "fechaISO": "2026-04-12",
      "esHoy": false,
      "liga": "nacional",
      "ligaNombre": "Primera Nacional",
      "local": {
        "nombre": "Dep. Madryn",
        "goles": null
      },
      "visitante": {
        "nombre": "Alte. Brown",
        "goles": null
      },
      "hora": "11:00",
      "minuto": null,
      "estado": "programado"
    },
    {
      "id": 125,
      "fecha": 9,
      "dia": "Dom 12/04",
      "fechaISO": "2026-04-12",
      "esHoy": false,
      "liga": "nacional",
      "ligaNombre": "Primera Nacional",
      "local": {
        "nombre": "Agropecuario",
        "goles": null
      },
      "visitante": {
        "nombre": "Gimnasia (J)",
        "goles": null
      },
      "hora": "11:00",
      "minuto": null,
      "estado": "programado"
    },
    {
      "id": 126,
      "fecha": 9,
      "dia": "Dom 12/04",
      "fechaISO": "2026-04-12",
      "esHoy": false,
      "liga": "nacional",
      "ligaNombre": "Primera Nacional",
      "local": {
        "nombre": "Chaco For Ever",
        "goles": null
      },
      "visitante": {
        "nombre": "All Boys",
        "goles": null
      },
      "hora": "12:00",
      "minuto": null,
      "estado": "programado"
    },
    {
      "id": 127,
      "fecha": 9,
      "dia": "Dom 12/04",
      "fechaISO": "2026-04-12",
      "esHoy": false,
      "liga": "nacional",
      "ligaNombre": "Primera Nacional",
      "local": {
        "nombre": "Central Norte",
        "goles": null
      },
      "visitante": {
        "nombre": "Mitre SdE",
        "goles": null
      },
      "hora": "12:00",
      "minuto": null,
      "estado": "programado"
    },
    {
      "id": 128,
      "fecha": 9,
      "dia": "Dom 12/04",
      "fechaISO": "2026-04-12",
      "esHoy": false,
      "liga": "nacional",
      "ligaNombre": "Primera Nacional",
      "local": {
        "nombre": "Güemes",
        "goles": null
      },
      "visitante": {
        "nombre": "San Martín (T)",
        "goles": null
      },
      "hora": "12:00",
      "minuto": null,
      "estado": "programado"
    },
    {
      "id": 129,
      "fecha": 9,
      "dia": "Dom 12/04",
      "fechaISO": "2026-04-12",
      "esHoy": false,
      "liga": "nacional",
      "ligaNombre": "Primera Nacional",
      "local": {
        "nombre": "Maipú",
        "goles": null
      },
      "visitante": {
        "nombre": "Colegiales",
        "goles": null
      },
      "hora": "13:30",
      "minuto": null,
      "estado": "programado"
    },
    {
      "id": 130,
      "fecha": 9,
      "dia": "Lun 13/04",
      "fechaISO": "2026-04-13",
      "esHoy": false,
      "liga": "nacional",
      "ligaNombre": "Primera Nacional",
      "local": {
        "nombre": "Chicago",
        "goles": null
      },
      "visitante": {
        "nombre": "Midland",
        "goles": null
      },
      "hora": "14:00",
      "minuto": null,
      "estado": "programado"
    },
    {
      "id": 131,
      "fecha": 9,
      "dia": "Lun 13/04",
      "fechaISO": "2026-04-13",
      "esHoy": false,
      "liga": "nacional",
      "ligaNombre": "Primera Nacional",
      "local": {
        "nombre": "Tristan Suárez",
        "goles": null
      },
      "visitante": {
        "nombre": "Atlético Rafaela",
        "goles": null
      },
      "hora": "15:00",
      "minuto": null,
      "estado": "programado"
    },
    {
      "id": 132,
      "fecha": 9,
      "dia": "Lun 13/04",
      "fechaISO": "2026-04-13",
      "esHoy": false,
      "liga": "nacional",
      "ligaNombre": "Primera Nacional",
      "local": {
        "nombre": "San Martín",
        "goles": null
      },
      "visitante": {
        "nombre": "Atlanta",
        "goles": null
      },
      "hora": "16:30",
      "minuto": null,
      "estado": "programado"
    },
    {
      "id": 137,
      "fecha": 10,
      "dia": "Sáb 11/04",
      "fechaISO": "2026-04-11",
      "esHoy": false,
      "liga": "bmetro",
      "ligaNombre": "Primera B Metropolitana",
      "local": {
        "nombre": "Villa Dalmine",
        "goles": null
      },
      "visitante": {
        "nombre": "Laferrere",
        "goles": null
      },
      "hora": "10:30",
      "minuto": null,
      "estado": "programado"
    },
    {
      "id": 138,
      "fecha": 10,
      "dia": "Sáb 11/04",
      "fechaISO": "2026-04-11",
      "esHoy": false,
      "liga": "bmetro",
      "ligaNombre": "Primera B Metropolitana",
      "local": {
        "nombre": "Real Pilar",
        "goles": null
      },
      "visitante": {
        "nombre": "Armenio",
        "goles": null
      },
      "hora": "10:30",
      "minuto": null,
      "estado": "programado"
    },
    {
      "id": 139,
      "fecha": 10,
      "dia": "Sáb 11/04",
      "fechaISO": "2026-04-11",
      "esHoy": false,
      "liga": "bmetro",
      "ligaNombre": "Primera B Metropolitana",
      "local": {
        "nombre": "San Carlos",
        "goles": null
      },
      "visitante": {
        "nombre": "Argentino (Q)",
        "goles": null
      },
      "hora": "10:30",
      "minuto": null,
      "estado": "programado"
    },
    {
      "id": 140,
      "fecha": 10,
      "dia": "Sáb 11/04",
      "fechaISO": "2026-04-11",
      "esHoy": false,
      "liga": "bmetro",
      "ligaNombre": "Primera B Metropolitana",
      "local": {
        "nombre": "San Martín (Bur.)",
        "goles": null
      },
      "visitante": {
        "nombre": "CADU",
        "goles": null
      },
      "hora": "10:30",
      "minuto": null,
      "estado": "programado"
    },
    {
      "id": 141,
      "fecha": 10,
      "dia": "Sáb 11/04",
      "fechaISO": "2026-04-11",
      "esHoy": false,
      "liga": "bmetro",
      "ligaNombre": "Primera B Metropolitana",
      "local": {
        "nombre": "Italiano",
        "goles": null
      },
      "visitante": {
        "nombre": "Comunicaciones",
        "goles": null
      },
      "hora": "10:30",
      "minuto": null,
      "estado": "programado"
    },
    {
      "id": 142,
      "fecha": 10,
      "dia": "Sáb 11/04",
      "fechaISO": "2026-04-11",
      "esHoy": false,
      "liga": "bmetro",
      "ligaNombre": "Primera B Metropolitana",
      "local": {
        "nombre": "Merlo",
        "goles": null
      },
      "visitante": {
        "nombre": "Ituzaingó",
        "goles": null
      },
      "hora": "13:00",
      "minuto": null,
      "estado": "programado"
    },
    {
      "id": 143,
      "fecha": 10,
      "dia": "Dom 12/04",
      "fechaISO": "2026-04-12",
      "esHoy": false,
      "liga": "bmetro",
      "ligaNombre": "Primera B Metropolitana",
      "local": {
        "nombre": "Camioneros",
        "goles": null
      },
      "visitante": {
        "nombre": "Dock Sud",
        "goles": null
      },
      "hora": "10:00",
      "minuto": null,
      "estado": "programado"
    },
    {
      "id": 144,
      "fecha": 4,
      "dia": "Sáb 11/04",
      "fechaISO": "2026-04-11",
      "esHoy": false,
      "liga": "federala",
      "ligaNombre": "Federal A",
      "local": {
        "nombre": "Alvarado",
        "goles": null
      },
      "visitante": {
        "nombre": "Kimberley",
        "goles": null
      },
      "hora": "10:30",
      "minuto": null,
      "estado": "programado"
    },
    {
      "id": 145,
      "fecha": 4,
      "dia": "Sáb 11/04",
      "fechaISO": "2026-04-11",
      "esHoy": false,
      "liga": "federala",
      "ligaNombre": "Federal A",
      "local": {
        "nombre": "Bartolomé Mitre",
        "goles": null
      },
      "visitante": {
        "nombre": "Sol De América",
        "goles": null
      },
      "hora": "11:30",
      "minuto": null,
      "estado": "programado"
    },
    {
      "id": 146,
      "fecha": 4,
      "dia": "Sáb 11/04",
      "fechaISO": "2026-04-11",
      "esHoy": false,
      "liga": "federala",
      "ligaNombre": "Federal A",
      "local": {
        "nombre": "Santamarina",
        "goles": null
      },
      "visitante": {
        "nombre": "Círculo Deportivo",
        "goles": null
      },
      "hora": "13:30",
      "minuto": null,
      "estado": "programado"
    },
    {
      "id": 147,
      "fecha": 4,
      "dia": "Sáb 11/04",
      "fechaISO": "2026-04-11",
      "esHoy": false,
      "liga": "federala",
      "ligaNombre": "Federal A",
      "local": {
        "nombre": "Gimnasia de Concepción",
        "goles": null
      },
      "visitante": {
        "nombre": "Independiente (Chi)",
        "goles": null
      },
      "hora": "14:00",
      "minuto": null,
      "estado": "programado"
    },
    {
      "id": 148,
      "fecha": 4,
      "dia": "Dom 12/04",
      "fechaISO": "2026-04-12",
      "esHoy": false,
      "liga": "federala",
      "ligaNombre": "Federal A",
      "local": {
        "nombre": "Germinal",
        "goles": null
      },
      "visitante": {
        "nombre": "Villa Mitre",
        "goles": null
      },
      "hora": "10:00",
      "minuto": null,
      "estado": "programado"
    },
    {
      "id": 149,
      "fecha": 4,
      "dia": "Dom 12/04",
      "fechaISO": "2026-04-12",
      "esHoy": false,
      "liga": "federala",
      "ligaNombre": "Federal A",
      "local": {
        "nombre": "Olimpo",
        "goles": null
      },
      "visitante": {
        "nombre": "Sol de Mayo",
        "goles": null
      },
      "hora": "10:30",
      "minuto": null,
      "estado": "programado"
    },
    {
      "id": 150,
      "fecha": 4,
      "dia": "Dom 12/04",
      "fechaISO": "2026-04-12",
      "esHoy": false,
      "liga": "federala",
      "ligaNombre": "Federal A",
      "local": {
        "nombre": "Juventud Unida (SL)",
        "goles": null
      },
      "visitante": {
        "nombre": "Dvo. Rincón",
        "goles": null
      },
      "hora": "10:30",
      "minuto": null,
      "estado": "programado"
    },
    {
      "id": 151,
      "fecha": 4,
      "dia": "Dom 12/04",
      "fechaISO": "2026-04-12",
      "esHoy": false,
      "liga": "federala",
      "ligaNombre": "Federal A",
      "local": {
        "nombre": "Cipolletti",
        "goles": null
      },
      "visitante": {
        "nombre": "Costa Brava",
        "goles": null
      },
      "hora": "10:30",
      "minuto": null,
      "estado": "programado"
    },
    {
      "id": 152,
      "fecha": 4,
      "dia": "Dom 12/04",
      "fechaISO": "2026-04-12",
      "esHoy": false,
      "liga": "federala",
      "ligaNombre": "Federal A",
      "local": {
        "nombre": "Defensores (VR)",
        "goles": null
      },
      "visitante": {
        "nombre": "Sp. Belgrano",
        "goles": null
      },
      "hora": "11:00",
      "minuto": null,
      "estado": "programado"
    },
    {
      "id": 153,
      "fecha": 4,
      "dia": "Dom 12/04",
      "fechaISO": "2026-04-12",
      "esHoy": false,
      "liga": "federala",
      "ligaNombre": "Federal A",
      "local": {
        "nombre": "CSCyD Gimnasia y Esgrima (Chivilcoy)",
        "goles": null
      },
      "visitante": {
        "nombre": "Sportivo LP",
        "goles": null
      },
      "hora": "11:00",
      "minuto": null,
      "estado": "programado"
    },
    {
      "id": 154,
      "fecha": 4,
      "dia": "Dom 12/04",
      "fechaISO": "2026-04-12",
      "esHoy": false,
      "liga": "federala",
      "ligaNombre": "Federal A",
      "local": {
        "nombre": "Argentino MM",
        "goles": null
      },
      "visitante": {
        "nombre": "Fundación Amigos por el Deporte",
        "goles": null
      },
      "hora": "11:00",
      "minuto": null,
      "estado": "programado"
    },
    {
      "id": 155,
      "fecha": 4,
      "dia": "Dom 12/04",
      "fechaISO": "2026-04-12",
      "esHoy": false,
      "liga": "federala",
      "ligaNombre": "Federal A",
      "local": {
        "nombre": "Douglas Haig",
        "goles": null
      },
      "visitante": {
        "nombre": "El Linqueño",
        "goles": null
      },
      "hora": "11:30",
      "minuto": null,
      "estado": "programado"
    },
    {
      "id": 156,
      "fecha": 4,
      "dia": "Dom 12/04",
      "fechaISO": "2026-04-12",
      "esHoy": false,
      "liga": "federala",
      "ligaNombre": "Federal A",
      "local": {
        "nombre": "San Martín (For)",
        "goles": null
      },
      "visitante": {
        "nombre": "Boca Unidos",
        "goles": null
      },
      "hora": "11:30",
      "minuto": null,
      "estado": "programado"
    },
    {
      "id": 157,
      "fecha": 4,
      "dia": "Dom 12/04",
      "fechaISO": "2026-04-12",
      "esHoy": false,
      "liga": "federala",
      "ligaNombre": "Federal A",
      "local": {
        "nombre": "Atenas (RC)",
        "goles": null
      },
      "visitante": {
        "nombre": "Huracán (LH)",
        "goles": null
      },
      "hora": "11:30",
      "minuto": null,
      "estado": "programado"
    },
    {
      "id": 158,
      "fecha": 4,
      "dia": "Dom 12/04",
      "fechaISO": "2026-04-12",
      "esHoy": false,
      "liga": "federala",
      "ligaNombre": "Federal A",
      "local": {
        "nombre": "9 de Julio (R)",
        "goles": null
      },
      "visitante": {
        "nombre": "Atlético Escobar",
        "goles": null
      },
      "hora": "12:00",
      "minuto": null,
      "estado": "programado"
    },
    {
      "id": 159,
      "fecha": 4,
      "dia": "Dom 12/04",
      "fechaISO": "2026-04-12",
      "esHoy": false,
      "liga": "federala",
      "ligaNombre": "Federal A",
      "local": {
        "nombre": "Sarmiento (LB)",
        "goles": null
      },
      "visitante": {
        "nombre": "Juv. Antoniana",
        "goles": null
      },
      "hora": "14:00",
      "minuto": null,
      "estado": "programado"
    },
    {
      "id": 160,
      "fecha": 4,
      "dia": "Lun 13/04",
      "fechaISO": "2026-04-13",
      "esHoy": false,
      "liga": "federala",
      "ligaNombre": "Federal A",
      "local": {
        "nombre": "Defensores Pto. Vilelas",
        "goles": null
      },
      "visitante": {
        "nombre": "Sarmiento (R)",
        "goles": null
      },
      "hora": "15:30",
      "minuto": null,
      "estado": "programado"
    },
    {
      "id": 162,
      "fecha": 7,
      "dia": "Sáb 11/04",
      "fechaISO": "2026-04-11",
      "esHoy": false,
      "liga": "primerac",
      "ligaNombre": "Primera C Metropolitana",
      "local": {
        "nombre": "Cañuelas",
        "goles": null
      },
      "visitante": {
        "nombre": "CA Atlas",
        "goles": null
      },
      "hora": "10:30",
      "minuto": null,
      "estado": "programado"
    },
    {
      "id": 163,
      "fecha": 7,
      "dia": "Sáb 11/04",
      "fechaISO": "2026-04-11",
      "esHoy": false,
      "liga": "primerac",
      "ligaNombre": "Primera C Metropolitana",
      "local": {
        "nombre": "Central Cordoba",
        "goles": null
      },
      "visitante": {
        "nombre": "Luján",
        "goles": null
      },
      "hora": "10:30",
      "minuto": null,
      "estado": "programado"
    },
    {
      "id": 164,
      "fecha": 7,
      "dia": "Sáb 11/04",
      "fechaISO": "2026-04-11",
      "esHoy": false,
      "liga": "primerac",
      "ligaNombre": "Primera C Metropolitana",
      "local": {
        "nombre": "Central Ballester",
        "goles": null
      },
      "visitante": {
        "nombre": "Fenix",
        "goles": null
      },
      "hora": "10:30",
      "minuto": null,
      "estado": "programado"
    },
    {
      "id": 165,
      "fecha": 7,
      "dia": "Sáb 11/04",
      "fechaISO": "2026-04-11",
      "esHoy": false,
      "liga": "primerac",
      "ligaNombre": "Primera C Metropolitana",
      "local": {
        "nombre": "Leandro N. Alem",
        "goles": null
      },
      "visitante": {
        "nombre": "Cambaceres",
        "goles": null
      },
      "hora": "10:30",
      "minuto": null,
      "estado": "programado"
    },
    {
      "id": 166,
      "fecha": 7,
      "dia": "Sáb 11/04",
      "fechaISO": "2026-04-11",
      "esHoy": false,
      "liga": "primerac",
      "ligaNombre": "Primera C Metropolitana",
      "local": {
        "nombre": "Paraguayo",
        "goles": null
      },
      "visitante": {
        "nombre": "Sacachispas",
        "goles": null
      },
      "hora": "10:30",
      "minuto": null,
      "estado": "programado"
    },
    {
      "id": 167,
      "fecha": 7,
      "dia": "Sáb 11/04",
      "fechaISO": "2026-04-11",
      "esHoy": false,
      "liga": "primerac",
      "ligaNombre": "Primera C Metropolitana",
      "local": {
        "nombre": "Mercedes",
        "goles": null
      },
      "visitante": {
        "nombre": "Argentino Rosario",
        "goles": null
      },
      "hora": "10:30",
      "minuto": null,
      "estado": "programado"
    },
    {
      "id": 168,
      "fecha": 7,
      "dia": "Sáb 11/04",
      "fechaISO": "2026-04-11",
      "esHoy": false,
      "liga": "primerac",
      "ligaNombre": "Primera C Metropolitana",
      "local": {
        "nombre": "JJ Urquiza",
        "goles": null
      },
      "visitante": {
        "nombre": "Estrella del Sur",
        "goles": null
      },
      "hora": "10:30",
      "minuto": null,
      "estado": "programado"
    },
    {
      "id": 169,
      "fecha": 7,
      "dia": "Dom 12/04",
      "fechaISO": "2026-04-12",
      "esHoy": false,
      "liga": "primerac",
      "ligaNombre": "Primera C Metropolitana",
      "local": {
        "nombre": "Claypole",
        "goles": null
      },
      "visitante": {
        "nombre": "Sp. Barracas",
        "goles": null
      },
      "hora": "10:30",
      "minuto": null,
      "estado": "programado"
    },
    {
      "id": 170,
      "fecha": 7,
      "dia": "Dom 12/04",
      "fechaISO": "2026-04-12",
      "esHoy": false,
      "liga": "primerac",
      "ligaNombre": "Primera C Metropolitana",
      "local": {
        "nombre": "Puerto Nuevo",
        "goles": null
      },
      "visitante": {
        "nombre": "Juventud Unida SM",
        "goles": null
      },
      "hora": "10:30",
      "minuto": null,
      "estado": "programado"
    },
    {
      "id": 171,
      "fecha": 7,
      "dia": "Dom 12/04",
      "fechaISO": "2026-04-12",
      "esHoy": false,
      "liga": "primerac",
      "ligaNombre": "Primera C Metropolitana",
      "local": {
        "nombre": "Centro Español",
        "goles": null
      },
      "visitante": {
        "nombre": "Berazategui",
        "goles": null
      },
      "hora": "10:30",
      "minuto": null,
      "estado": "programado"
    },
    {
      "id": 172,
      "fecha": 7,
      "dia": "Dom 12/04",
      "fechaISO": "2026-04-12",
      "esHoy": false,
      "liga": "primerac",
      "ligaNombre": "Primera C Metropolitana",
      "local": {
        "nombre": "Victoriano",
        "goles": null
      },
      "visitante": {
        "nombre": "CA Lugano",
        "goles": null
      },
      "hora": "10:30",
      "minuto": null,
      "estado": "programado"
    },
    {
      "id": 173,
      "fecha": 7,
      "dia": "Lun 13/04",
      "fechaISO": "2026-04-13",
      "esHoy": false,
      "liga": "primerac",
      "ligaNombre": "Primera C Metropolitana",
      "local": {
        "nombre": "Yupanqui",
        "goles": null
      },
      "visitante": {
        "nombre": "El Porvenir",
        "goles": null
      },
      "hora": "10:30",
      "minuto": null,
      "estado": "programado"
    },
    {
      "id": 174,
      "fecha": 7,
      "dia": "Lun 13/04",
      "fechaISO": "2026-04-13",
      "esHoy": false,
      "liga": "primerac",
      "ligaNombre": "Primera C Metropolitana",
      "local": {
        "nombre": "Muñiz",
        "goles": null
      },
      "visitante": {
        "nombre": "Leones de Rosario FC",
        "goles": null
      },
      "hora": "10:30",
      "minuto": null,
      "estado": "programado"
    }
  ]
}